[
  {
    "word": "소개",
    "translation": "представление",
    "transcription": "sogae",
    "description": "краткое знакомство или вводная информация",
    "audio": "audio/소개_tts.mp3"
  },
  {
    "word": "소개하다",
    "translation": "представлять; знакомить",
    "transcription": "sogaehada",
    "description": "знакомить людей или рассказывать о ком-то",
    "audio": "audio/소개하다_tts.mp3"
  },
  {
    "word": "소고기",
    "translation": "говядина",
    "transcription": "sogogi",
    "description": "мясо коровы",
    "audio": "audio/소고기_tts.mp3"
  },
  {
    "word": "소금",
    "translation": "соль",
    "transcription": "sogeum",
    "description": "поваренная соль как приправа",
    "audio": "audio/소금_tts.mp3"
  },
  {
    "word": "소리",
    "translation": "звук; голос",
    "transcription": "sori",
    "description": "любые слышимые колебания или речь",
    "audio": "audio/소리_tts.mp3"
  },
  {
    "word": "소설",
    "translation": "роман; повесть",
    "transcription": "soseol",
    "description": "художественное прозовое произведение",
    "audio": "audio/소설_tts.mp3"
  },
  {
    "word": "소설가",
    "translation": "писатель-романист",
    "transcription": "soseolga",
    "description": "автор художественных произведений",
    "audio": "audio/소설가_tts.mp3"
  },
  {
    "word": "소식",
    "translation": "новости",
    "transcription": "sosik",
    "description": "сведения или сообщения о событиях",
    "audio": "audio/소식_tts.mp3"
  },
  {
    "word": "소파",
    "translation": "диван",
    "transcription": "sopa",
    "description": "мягкая мебель для сидения",
    "audio": "audio/소파_tts.mp3"
  },
  {
    "word": "소포",
    "translation": "посылка",
    "transcription": "sopo",
    "description": "упакованная почтовая отправка",
    "audio": "audio/소포_tts.mp3"
  },
  {
    "word": "소풍",
    "translation": "пикник; экскурсия",
    "transcription": "sopung",
    "description": "короткая прогулка или выезд на природу",
    "audio": "audio/소풍_tts.mp3"
  },
  {
    "word": "소화제",
    "translation": "желудочные капли",
    "transcription": "sohwaje",
    "description": "лекарство, облегчающее пищеварение",
    "audio": "audio/소화제_tts.mp3"
  },
  {
    "word": "속",
    "translation": "внутри",
    "transcription": "sok",
    "description": "внутреннее пространство чего-либо",
    "audio": "audio/속_tts.mp3"
  },
  {
    "word": "손",
    "translation": "рука (ладонь)",
    "transcription": "son",
    "description": "кисть руки человека",
    "audio": "audio/손_tts.mp3"
  },
  {
    "word": "손가락",
    "translation": "палец руки",
    "transcription": "songarak",
    "description": "один из пяти пальцев кисти",
    "audio": "audio/손가락_tts.mp3"
  },
  {
    "word": "손님",
    "translation": "гость; клиент",
    "transcription": "sonnim",
    "description": "посетитель или покупатель",
    "audio": "audio/손님_tts.mp3"
  },
  {
    "word": "손수건",
    "translation": "носовой платок",
    "transcription": "sonsugeon",
    "description": "небольшой платок для лица и рук",
    "audio": "audio/손수건_tts.mp3"
  },
  {
    "word": "송이",
    "translation": "гроздь; штука (цветок)",
    "transcription": "songi",
    "description": "счётное слово для гроздей, цветов",
    "audio": "audio/송이_tts.mp3"
  },
  {
    "word": "쇼핑",
    "translation": "шопинг",
    "transcription": "syoping",
    "description": "походы по магазинам за покупками",
    "audio": "audio/쇼핑_tts.mp3"
  },
  {
    "word": "수건",
    "translation": "полотенце",
    "transcription": "sugeon",
    "description": "ткань для вытирания после воды",
    "audio": "audio/수건_tts.mp3"
  }
]